{"state_name":"Illinois","id":5772,"state":"IL","district":14,"total_receipts":2569631,"total_disbursements":1059581,"cook_rating":6,"inside_rating":8,"crystal_rating":6,"news_total":47,"created_at":"2018-10-11T20:11:18.477Z","updated_at":"2018-10-11T22:48:50.086Z","candidates":[{"full_name":"Chris Lauzen","id":15481,"fec_id":"H8IL14075","first_name":"Chris","last_name":"Lauzen","party":"R","status":"O","receipts":0,"disbursements":84,"news_hits":3,"created_at":"2018-10-11T20:11:32.737Z","updated_at":"2018-10-11T21:18:02.572Z","race_id":5772},{"full_name":"George Weber","id":15483,"fec_id":"H8IL14158","first_name":"George","last_name":"Weber","party":"D","status":"C","receipts":17255,"disbursements":17255,"news_hits":413000,"created_at":"2018-10-11T20:11:32.738Z","updated_at":"2018-10-11T21:18:57.023Z","race_id":5772},{"full_name":"Victor Swanson","id":15482,"fec_id":"H8IL14141","first_name":"Victor","last_name":"Swanson","party":"D","status":"C","receipts":80410,"disbursements":80410,"news_hits":230000,"created_at":"2018-10-11T20:11:32.737Z","updated_at":"2018-10-11T21:19:39.339Z","race_id":5772},{"full_name":"Matt Brolley","id":15484,"fec_id":"H8IL14166","first_name":"Matt","last_name":"Brolley","party":"D","status":"C","receipts":166694,"disbursements":166476,"news_hits":1,"created_at":"2018-10-11T20:11:32.738Z","updated_at":"2018-10-11T21:20:04.741Z","race_id":5772},{"full_name":"Lauren Underwood","id":15485,"fec_id":"H8IL14174","first_name":"Lauren","last_name":"Underwood","party":"D","status":"C","receipts":1129203,"disbursements":477318,"news_hits":47,"created_at":"2018-10-11T20:11:32.743Z","updated_at":"2018-10-11T20:21:24.027Z","race_id":5772},{"full_name":"Dennis Anderson","id":17268,"fec_id":"H2IL14078","first_name":"Dennis","last_name":"Anderson","party":"D","status":"C","receipts":0,"disbursements":0,"news_hits":3180000,"created_at":"2018-10-11T20:11:50.550Z","updated_at":"2018-10-11T21:44:27.037Z","race_id":5772},{"full_name":"Linda Lavia","id":17516,"fec_id":"H8IL14059","first_name":"Linda","last_name":"Lavia","party":"D","status":"O","receipts":0,"disbursements":0,"news_hits":1,"created_at":"2018-10-11T20:11:53.838Z","updated_at":"2018-10-11T21:46:16.367Z","race_id":5772},{"full_name":"Joe Serra","id":17584,"fec_id":"H8IL14117","first_name":"Joe","last_name":"Serra","party":"D","status":"O","receipts":0,"disbursements":0,"news_hits":25,"created_at":"2018-10-11T20:11:54.501Z","updated_at":"2018-10-11T21:46:59.400Z","race_id":5772},{"full_name":"Randy Hultgren","id":18264,"fec_id":"H0IL14080","first_name":"Randy","last_name":"Hultgren","party":"R","status":"I","receipts":1440428,"disbursements":582263,"news_hits":27,"created_at":"2018-10-11T20:12:05.532Z","updated_at":"2018-10-11T21:52:56.714Z","race_id":5772}]}